{
  "entityType" : "ENTITY_GROUP",
  "entity" : {
    "additionalInfo" : null,
    "configuration" : {
      "columns" : [ {
        "type" : "ENTITY_FIELD",
        "key" : "created_time",
        "sortOrder" : "DESC"
      }, {
        "type" : "ENTITY_FIELD",
        "key" : "name",
        "sortOrder" : "NONE"
      }, {
        "type" : "ENTITY_FIELD",
        "key" : "type",
        "sortOrder" : "NONE"
      } ],
      "settings" : { },
      "actions" : { }
    },
    "edgeGroupAll" : false,
    "externalId" : null,
    "groupAll" : true,
    "id" : {
      "entityType" : "ENTITY_GROUP",
      "id" : "92fe8f20-c637-11ec-acb5-2b05b2d25c52"
    },
    "name" : "All",
    "ownerId" : {
      "entityType" : "CUSTOMER",
      "id" : "92e561d0-c637-11ec-acb5-2b05b2d25c52"
    },
    "type" : "ASSET"
  },
  "relations" : [ ],
  "attributes" : {
    "SERVER_SCOPE" : [ ]
  },
  "groupEntities" : true
}